README.rst
setup.cfg
setup.py
frhdtools/Decode.py
frhdtools/Encode.py
frhdtools/Segment.py
frhdtools/Track.py
frhdtools/__init__.py
frhdtools.egg-info/PKG-INFO
frhdtools.egg-info/SOURCES.txt
frhdtools.egg-info/dependency_links.txt
frhdtools.egg-info/top_level.txt