Metadata-Version: 1.1
Name: frhdtools
Version: 0.0.3.6
Summary: Library to work with Free Rider HD Tracks
Home-page: https://github.com/maxmillion18/frhdtools
Author: maxmillion18
Author-email: icantpostmyemailhere@gmail.com
License: MIT License
Keywords: development freeriderhd freerider code track tracks
Platform: UNKNOWN
Classifier: Development Status :: 2 - Pre-Alpha
Classifier: Intended Audience :: Developers
Classifier: Topic :: Software Development :: Code Generators
Classifier: License :: OSI Approved :: MIT License
Classifier: Programming Language :: Python :: 3 :: Only
